sugar_spider_serpapi/__init__.py
sugar_spider_serpapi/common.py
sugar_spider_serpapi/example.py
sugar_spider_serpapi/scripts.py
sugar_spider_serpapi/explorer/__init__.py
sugar_spider_serpapi/explorer/keyword.py
sugar_spider_serpapi/explorer/product.py
sugar_spider_serpapi/metastore/__init__.py
sugar_spider_serpapi/metastore/core.py
sugar_spider_serpapi/metastore/redis.py
sugar_spider_serpapi/scraper/__init__.py
sugar_spider_serpapi/scraper/product.py
sugar_spider_serpapi/serpapi_client/__init__.py
sugar_spider_serpapi/serpapi_client/conf.py
sugar_spider_serpapi/serpapi_client/exception.py
sugar_spider_serpapi/serpapi_client/google/__init__.py
sugar_spider_serpapi/serpapi_client/google/client.py
sugar_spider_serpapi/serpapi_client/handler/__init__.py
sugar_spider_serpapi/serpapi_client/handler/kafka.py
sugar_spider_serpapi/serpapi_client/handler/local.py
sugar_spider_serpapi/serpapi_client/handler/parser.py
sugar_spider_serpapi-0.0.1.dist-info/METADATA
sugar_spider_serpapi-0.0.1.dist-info/WHEEL
sugar_spider_serpapi-0.0.1.dist-info/entry_points.txt
sugar_spider_serpapi-0.0.1.dist-info/top_level.txt
sugar_spider_serpapi-0.0.1.dist-info/RECORD
